{
  "fragments": [
    {
      "direction": "Input",
      "entityId": "e9528e23-1ec3-4a75-b8c4-26a9d417e5ad",
      "entityType": "fragment",
      "exchangeValues": {
        "0": 1.0,
        "1": 1.0
      },
      "externalId": "bg-glass-GLO",
      "flow": {
        "externalId": "c3fd9530-3e9b-44b5-8833-9e544937a6e9",
        "origin": "ecoinvent.3.7.1.cutoff"
      },
      "isBackground": true,
      "isBalanceFlow": false,
      "isPrivate": false,
      "parent": null,
      "tags": {
        "Comment": "",
        "Name": "packaging glass, white",
        "StageName": "packaging glass production, white, without cullet"
      },
      "terminations": {
        "default": {
          "externalId": "2326311d-6d7c-5bd4-bc1b-739817040bbc",
          "origin": "ecoinvent.3.10.cutoff",
          "termFlow": "c3fd9530-3e9b-44b5-8833-9e544937a6e9"
        }
      }
    }
  ]
}